{
    "id": "1hG-RMSsHvR8ShUrltBy9b-lN5H3vcpqveD4II4BxL2I",
    "name": "Sales Techniques:  Show Me the Money: Mastering the ROI Sales Technique",
    "mimeType": "application/vnd.google-apps.presentation",
    "createdTime": "2024-11-04T20:55:36.458Z",
    "modifiedTime": "2024-11-08T19:10:38.041Z",
    "owners": [
        {
            "kind": "drive#user",
            "displayName": "Jonalyn Pelobello (Culyn Robinson)",
            "photoLink": "https://lh3.googleusercontent.com/a-/ALV-UjUu0NXvttjapYUXZHT2Nhzys-wAfhGwZjZ9X2GEJXPl4gMJ-2Oy=s64",
            "me": false,
            "permissionId": "06973847733891131415",
            "emailAddress": "j.pelobello@us.411locals.com"
        }
    ],
    "lastModifyingUser": {
        "kind": "drive#user",
        "displayName": "Jonalyn Pelobello (Culyn Robinson)",
        "photoLink": "https://lh3.googleusercontent.com/a-/ALV-UjUu0NXvttjapYUXZHT2Nhzys-wAfhGwZjZ9X2GEJXPl4gMJ-2Oy=s64",
        "me": false,
        "permissionId": "06973847733891131415",
        "emailAddress": "j.pelobello@us.411locals.com"
    },
    "size": "593676"
}